{
  "lastUpdated": "2026-05-22 05:06:58",
  "date": "2026.05.22",
  "kospi": {
    "name": "KOSPI",
    "current": "7865.37",
    "change": "49.78",
    "changePct": "0.64",
    "direction": "up",
    "volume": "359240",
    "tradeAmount": "23514411"
  },
  "stocks": [
    {
      "code": "005930",
      "name": "삼성전자",
      "nameEn": "Samsung Electronics",
      "current": "293750",
      "change": "-5750",
      "changePct": "-1.92",
      "direction": "down",
      "volume": "13134396",
      "high": "300500",
      "low": "292000",
      "open": "300000",
      "marketCap": "0"
    },
    {
      "code": "000660",
      "name": "SK하이닉스",
      "nameEn": "SK Hynix",
      "current": "1944000",
      "change": "4000",
      "changePct": "0.21",
      "direction": "up",
      "volume": "2244322",
      "high": "1952000",
      "low": "1912000",
      "open": "1942000",
      "marketCap": "0"
    },
    {
      "code": "003550",
      "name": "LG",
      "nameEn": "LG",
      "current": "119500",
      "change": "-3500",
      "changePct": "-2.85",
      "direction": "down",
      "volume": "773952",
      "high": "120400",
      "low": "116000",
      "open": "119300",
      "marketCap": "0"
    },
    {
      "code": "035420",
      "name": "NAVER",
      "nameEn": "NAVER",
      "current": "205000",
      "change": "5500",
      "changePct": "2.76",
      "direction": "up",
      "volume": "579563",
      "high": "207000",
      "low": "199300",
      "open": "201500",
      "marketCap": "0"
    }
  ],
  "exchangeRates": [
    {
      "pair": "USD/KRW",
      "name": "미국 USD",
      "value": "1514.80",
      "change": "9.30",
      "direction": "up"
    },
    {
      "pair": "JPY/KRW",
      "name": "일본 JPY(100엔)",
      "value": "952.35",
      "change": "5.58",
      "direction": "up"
    },
    {
      "pair": "EUR/KRW",
      "name": "유럽연합 EUR",
      "value": "1759.67",
      "change": "10.81",
      "direction": "up"
    },
    {
      "pair": "CNY/KRW",
      "name": "중국 CNY",
      "value": "222.75",
      "change": "1.35",
      "direction": "up"
    }
  ],
  "oilPrices": [
    {
      "code": "OIL_CL",
      "name": "WTI",
      "value": "96.35",
      "change": "1.91",
      "direction": "down",
      "unit": "USD/barrel"
    },
    {
      "code": "GOLD",
      "name": "Gold",
      "value": "4542.5",
      "change": "7.20",
      "direction": "up",
      "unit": "USD/oz"
    },
    {
      "code": "GOLD",
      "name": "Gold",
      "value": "220385.67",
      "change": "659.17",
      "direction": "up",
      "unit": "USD/oz"
    },
    {
      "code": "OIL_BRT",
      "name": "Brent",
      "value": "102.58",
      "change": "0",
      "direction": "up",
      "unit": "USD/barrel"
    },
    {
      "code": "OIL_DU",
      "name": "Dubai",
      "value": "102.92",
      "change": "0",
      "direction": "up",
      "unit": "USD/barrel"
    }
  ],
  "news": [
    {
      "title": "‘1.6兆 잭팟’ 터진 삼성전기 주가도 질주…장중 신고가 경신 [줍줍리포트]",
      "link": "https://finance.naver.com/news/news_read.naver?article_id=0004623646&office_id=011&mode=mainnews&type=&date=2026-05-22&page=1"
    },
    {
      "title": "코스닥, ‘국민성장펀드’ 완판에 5%대 급등…코스피는 강보합",
      "link": "https://finance.naver.com/news/news_read.naver?article_id=0006287937&office_id=018&mode=mainnews&type=&date=2026-05-22&page=1"
    },
    {
      "title": "자산 재분배·퀀트 모델 활용…미국 개미의 ‘AI 거품’ 대응법",
      "link": "https://finance.naver.com/news/news_read.naver?article_id=0003977896&office_id=023&mode=mainnews&type=&date=2026-05-22&page=1"
    },
    {
      "title": "삼전닉스 신용융자 7조 첫 돌파… ‘빚투’도 반도체에 몰렸다",
      "link": "https://finance.naver.com/news/news_read.naver?article_id=0002793036&office_id=021&mode=mainnews&type=&date=2026-05-22&page=1"
    },
    {
      "title": "‘AI 종합 선물 세트’ SK그룹, 순매수 상위권 싹쓸이 [주식 초고수는 지금]",
      "link": "https://finance.naver.com/news/news_read.naver?article_id=0004623631&office_id=011&mode=mainnews&type=&date=2026-05-22&page=1"
    },
    {
      "title": "RIA 100% 공제 막차 오는데…서학개미 국장 복귀 서두를까",
      "link": "https://finance.naver.com/news/news_read.naver?article_id=0001144438&office_id=417&mode=mainnews&type=&date=2026-05-22&page=1"
    },
    {
      "title": "세제 혜택에 손실 방어까지… 국민성장펀드에 개미들 ‘오픈런’",
      "link": "https://finance.naver.com/news/news_read.naver?article_id=0001166451&office_id=366&mode=mainnews&type=&date=2026-05-22&page=1"
    },
    {
      "title": "대기업 지정 콜마그룹주, K-뷰티 타고 고공행진",
      "link": "https://finance.naver.com/news/news_read.naver?article_id=0002647062&office_id=016&mode=mainnews&type=&date=2026-05-22&page=1"
    }
  ]
}